_version.py
teachbooks_sphinx_tippy.py
teachbooks_sphinx_tippy-1.0.15.dist-info/licenses/LICENSE
teachbooks_sphinx_tippy-1.0.15.dist-info/METADATA
teachbooks_sphinx_tippy-1.0.15.dist-info/WHEEL
teachbooks_sphinx_tippy-1.0.15.dist-info/top_level.txt
teachbooks_sphinx_tippy-1.0.15.dist-info/RECORD
