Metadata-Version: 2.4
Name: teachbooks_sphinx_tippy
Version: 1.0.15
Summary: Get rich tool tips in your sphinx book!
Author-email: Dennis den Ouden-van der Horst <d.denouden-vanderhorst@tudelft.nl>
License: MIT License
Project-URL: Home, https://github.com/TeachBooks/teachbooks-sphinx-tippy
Project-URL: Documentation, https://github.com/TeachBooks/teachbooks-sphinx-tippy
Keywords: sphinx,tooltip,tippy,teachbooks
Classifier: Development Status :: 4 - Beta
Classifier: Framework :: Sphinx :: Extension
Classifier: Intended Audience :: Developers
Classifier: License :: OSI Approved :: MIT License
Classifier: Programming Language :: Python :: 3
Requires-Python: >=3.8
License-File: LICENSE
Requires-Dist: sphinx>4
Requires-Dist: beautifulsoup4
Requires-Dist: jinja2
Requires-Dist: requests
Provides-Extra: testing
Requires-Dist: pytest; extra == "testing"
Requires-Dist: sphinx-pytest; extra == "testing"
Requires-Dist: pytest-regressions; extra == "testing"
Provides-Extra: docs
Requires-Dist: myst-parser; extra == "docs"
Requires-Dist: furo; extra == "docs"
Dynamic: license-file
